alembic_dump/__init__.py
alembic_dump/config.py
alembic_dump/core.py
alembic_dump/db.py
alembic_dump/masking.py
alembic_dump/secrets.py
alembic_dump/ssh.py
alembic_dump/utils.py
alembic_dump-0.1.7.dist-info/METADATA
alembic_dump-0.1.7.dist-info/WHEEL
alembic_dump-0.1.7.dist-info/licenses/LICENSE
alembic_dump-0.1.7.dist-info/RECORD
