Metadata-Version: 2.4
Name: alembic-dump
Version: 0.1.7
Summary: A Python library to dump, load, and mask data between databases in Alembic-managed environments, with SSH tunnel support.
Project-URL: Homepage, https://github.com/jaeyoung0509/alembic-dump
Author-email: Jaeyoung <jaeyoung0509@naver.com>
License: MIT License
License-File: LICENSE
Keywords: alembic,anonymization,copy,database,db,dump,load,masking,migration,mysql,postgresql,schema,sqlalchemy,ssh,tunnel
Classifier: Development Status :: 3 - Alpha
Classifier: Intended Audience :: Developers
Classifier: License :: OSI Approved :: MIT License
Classifier: Operating System :: OS Independent
Classifier: Programming Language :: Python
Classifier: Programming Language :: Python :: 3
Classifier: Programming Language :: Python :: 3.9
Classifier: Programming Language :: Python :: 3.10
Classifier: Programming Language :: Python :: 3.11
Classifier: Programming Language :: Python :: 3.12
Classifier: Topic :: Database
Classifier: Topic :: Software Development :: Libraries :: Python Modules
Classifier: Topic :: Utilities
Requires-Python: >=3.9
Requires-Dist: alembic>=1.12.0
Requires-Dist: faker>=18.0.0
Requires-Dist: pydantic-settings>=2.0.0
Requires-Dist: pydantic>=2.0.0
Requires-Dist: python-dotenv>=1.0.0
Requires-Dist: sqlalchemy>=2.0.0
Requires-Dist: sshtunnel>=0.4.0
Provides-Extra: aws
Requires-Dist: boto3-stubs[secretsmanager]>=1.28.0; extra == 'aws'
Requires-Dist: boto3>=1.28.0; extra == 'aws'
Provides-Extra: dev
Requires-Dist: black; extra == 'dev'
Requires-Dist: build; extra == 'dev'
Requires-Dist: docker>=7.0.0; extra == 'dev'
Requires-Dist: isort; extra == 'dev'
Requires-Dist: mypy; extra == 'dev'
Requires-Dist: psycopg2-binary>=2.9.5; extra == 'dev'
Requires-Dist: pytest-cov; extra == 'dev'
Requires-Dist: pytest>=8.0.0; extra == 'dev'
Requires-Dist: ruff; extra == 'dev'
Requires-Dist: sphinx; extra == 'dev'
Requires-Dist: sphinx-rtd-theme; extra == 'dev'
Requires-Dist: twine>=4.0.0; extra == 'dev'
Provides-Extra: vault
Requires-Dist: hvac>=1.0.0; extra == 'vault'
